timer_bar/__init__.py
timer_bar/main.py
timer_bar-1.0.2.dist-info/METADATA
timer_bar-1.0.2.dist-info/WHEEL
timer_bar-1.0.2.dist-info/licenses/LICENSE
timer_bar-1.0.2.dist-info/RECORD
