Metadata-Version: 2.1
Name: timer_bar
Version: 1.0.2
Summary: Simple console graphic to show progress of a process
Project-URL: Homepage, https://github.com/jkgriffiths93/timer_bar
Author-email: Jeff Griffiths <jkgriffiths93@gmail.com>
License-File: LICENSE
Classifier: License :: OSI Approved :: MIT License
Classifier: Operating System :: OS Independent
Classifier: Programming Language :: Python :: 3
Requires-Python: >=3.7
